workerlib/__init__.py
workerlib/connection.py
workerlib/consumer.py
workerlib/mq_queue.py
workerlib/pool.py
workerlib/producer.py
workerlib/retry.py
workerlib-0.3.4.dist-info/METADATA
workerlib-0.3.4.dist-info/WHEEL
workerlib-0.3.4.dist-info/top_level.txt
workerlib-0.3.4.dist-info/RECORD
