Metadata-Version: 2.4
Name: workerlib
Version: 0.3.4
Summary: Async RabbitMQ worker utilities
Author-email: YOUR_NAME <your.email@example.com>
Maintainer-email: YOUR_NAME <your.email@example.com>
Project-URL: Homepage, https://github.com/ametist-dev/workerlib
Project-URL: Repository, https://github.com/ametist-dev/workerlib
Project-URL: Issues, https://github.com/ametist-dev/workerlib/issues
Keywords: async,rabbitmq,aio-pika,workers
Classifier: Programming Language :: Python :: 3
Classifier: Programming Language :: Python :: 3.10
Classifier: Programming Language :: Python :: 3.11
Classifier: Programming Language :: Python :: 3.12
Classifier: Programming Language :: Python :: 3.13
Classifier: License :: OSI Approved :: MIT License
Classifier: Operating System :: OS Independent
Classifier: Intended Audience :: Developers
Classifier: Topic :: Software Development :: Libraries
Classifier: Development Status :: 4 - Beta
Requires-Python: >=3.10
Requires-Dist: aio-pika<10,>=9.0.0
